Workbook

Sheet Simulador
B1: SIMULADOR DE INVESTIMENTOS EM FIIs
B3: Aporte mensal, patrimônio, dividendos e divisão da carteira por perfil
B5: Você preenche | C5: Calculado (não editar)
B7: CONFIGURAÇÕES
B8: Salário mensal | D8: 3000
B9: Rendimento mensal da carteira (dividendos) | D9: 0.008
B10: % do salário sugerido para investir | D10: 0.3
B11: Sugestão de aporte mensal | D11: =salario*pct_sugestao -> 900
B13: INVESTIMENTO MENSAL — AS CINCO PERGUNTAS DE NEGÓCIO
D14: Valor informado | E14: Com a sugestão
B15: 1. Quanto investir por mês? | D15: 500 | E15: =sugestao_aporte -> 900
B16: 2. Por quantos anos? | D16: 10 | E16: =qtd_anos -> 10
B17: 3. Qual a taxa de rendimento mensal? | D17: 0.009 | E17: =taxa_mensal -> 0.009
B18: 4. Quanto de patrimônio vou acumular? | D18: =FV(taxa_mensal,qtd_anos*12,-aporte) -> 107249.33 | E18: =FV(taxa_mensal,qtd_anos*12,-sugestao_aporte) -> 193048.8
B19: 5. Quanto vou receber de dividendos por mês? | D19: =patrimonio*rendimento_carteira -> 857.99467 | E19: =E18*rendimento_carteira -> 1544.3904
B20: Total aportado no período | D20: =aporte*qtd_anos*12 -> 60000 | E20: =sugestao_aporte*qtd_anos*12 -> 108000
B21: Ganho com rendimentos | D21: =D18-D20 -> 47249.334 | E21: =E18-E20 -> 85048.801
B23: CENÁRIOS — PATRIMÔNIO E DIVIDENDOS POR PRAZO
B24: Prazo (anos) | C24: Patrimônio | D24: Dividendos/mês | E24: Patrimônio c/ sugestão | F24: Dividendos c/ sugestão
B25: 2 | C25: =FV(taxa_mensal,$B25*12,-aporte) -> 13327.989 | D25: =C25*rendimento_carteira -> 106.62391 | E25: =FV(taxa_mensal,$B25*12,-sugestao_aporte) -> 23990.38 | F25: =E25*rendimento_carteira -> 191.92304
B26: 5 | C26: =FV(taxa_mensal,$B26*12,-aporte) -> 39548.157 | D26: =C26*rendimento_carteira -> 316.38525 | E26: =FV(taxa_mensal,$B26*12,-sugestao_aporte) -> 71186.682 | F26: =E26*rendimento_carteira -> 569.49346
B27: 10 | C27: =FV(taxa_mensal,$B27*12,-aporte) -> 107249.33 | D27: =C27*rendimento_carteira -> 857.99467 | E27: =FV(taxa_mensal,$B27*12,-sugestao_aporte) -> 193048.8 | F27: =E27*rendimento_carteira -> 1544.3904
B28: 20 | C28: =FV(taxa_mensal,$B28*12,-aporte) -> 421542.22 | D28: =C28*rendimento_carteira -> 3372.3378 | E28: =FV(taxa_mensal,$B28*12,-sugestao_aporte) -> 758776 | F28: =E28*rendimento_carteira -> 6070.208
B29: 30 | C29: =FV(taxa_mensal,$B29*12,-aporte) -> 1342573.8 | D29: =C29*rendimento_carteira -> 10740.59 | E29: =FV(taxa_mensal,$B29*12,-sugestao_aporte) -> 2416632.8 | F29: =E29*rendimento_carteira -> 19333.062
B31: DIVISÃO DO APORTE POR PERFIL DE INVESTIDOR
B32: Perfil de investidor | C32: Moderado
B33: Valor mensal a investir | C33: =aporte -> 500
B35: Tipo de FII | C35: % sugerido | D35: Valor (R$)
B36: PAPEL | C36: =VLOOKUP(perfil&"-"&$B36,Apoio!$A:$D,4,FALSE()) -> 0.3 | D36: =C36*$C$33 -> 150
B37: TIJOLO | C37: =VLOOKUP(perfil&"-"&$B37,Apoio!$A:$D,4,FALSE()) -> 0.3 | D37: =C37*$C$33 -> 150
B38: HÍBRIDOS | C38: =VLOOKUP(perfil&"-"&$B38,Apoio!$A:$D,4,FALSE()) -> 0.1 | D38: =C38*$C$33 -> 50
B39: FOFs | C39: =VLOOKUP(perfil&"-"&$B39,Apoio!$A:$D,4,FALSE()) -> 0.1 | D39: =C39*$C$33 -> 50
B40: DESENVOLVIMENTO | C40: =VLOOKUP(perfil&"-"&$B40,Apoio!$A:$D,4,FALSE()) -> 0.1 | D40: =C40*$C$33 -> 50
B41: HOTELARIA | C41: =VLOOKUP(perfil&"-"&$B41,Apoio!$A:$D,4,FALSE()) -> 0.1 | D41: =C41*$C$33 -> 50
B42: TOTAL | C42: =SUM(C36:C41) -> 1 | D42: =SUM(D36:D41) -> 500
B44: Os percentuais são apenas um exemplo didático, não uma recomendação de investimento. Edite-os na aba Apoio (cada perfil deve somar 100%).

Sheet Apoio
A1: TABELA DE APOIO — PERCENTUAL POR PERFIL E TIPO DE FII
A2: Edite apenas a coluna % (amarelo). A chave é montada pela fórmula =Perfil&"-"&Tipo e é usada pelo PROCV do Simulador.
A4: CHAVE | B4: PERFIL | C4: TIPO DE FII | D4: % | F4: PERFIL | G4: SOMA DOS % | H4: STATUS
A5: =B5&"-"&C5 -> Conservador-PAPEL | B5: Conservador | C5: PAPEL | D5: 0.25 | F5: Conservador | G5: =SUMIF($B:$B,F5,$D:$D) -> 1 | H5: =IF(ROUND(G5,4)=1,"OK","Ajustar") -> OK
A6: =B6&"-"&C6 -> Conservador-TIJOLO | B6: Conservador | C6: TIJOLO | D6: 0.45 | F6: Moderado | G6: =SUMIF($B:$B,F6,$D:$D) -> 1 | H6: =IF(ROUND(G6,4)=1,"OK","Ajustar") -> OK
A7: =B7&"-"&C7 -> Conservador-HÍBRIDOS | B7: Conservador | C7: HÍBRIDOS | D7: 0.15 | F7: Agressivo | G7: =SUMIF($B:$B,F7,$D:$D) -> 1 | H7: =IF(ROUND(G7,4)=1,"OK","Ajustar") -> OK
A8: =B8&"-"&C8 -> Conservador-FOFs | B8: Conservador | C8: FOFs | D8: 0.15
A9: =B9&"-"&C9 -> Conservador-DESENVOLVIMENTO | B9: Conservador | C9: DESENVOLVIMENTO | D9: 0
A10: =B10&"-"&C10 -> Conservador-HOTELARIA | B10: Conservador | C10: HOTELARIA | D10: 0
A11: =B11&"-"&C11 -> Moderado-PAPEL | B11: Moderado | C11: PAPEL | D11: 0.3
A12: =B12&"-"&C12 -> Moderado-TIJOLO | B12: Moderado | C12: TIJOLO | D12: 0.3
A13: =B13&"-"&C13 -> Moderado-HÍBRIDOS | B13: Moderado | C13: HÍBRIDOS | D13: 0.1
A14: =B14&"-"&C14 -> Moderado-FOFs | B14: Moderado | C14: FOFs | D14: 0.1
A15: =B15&"-"&C15 -> Moderado-DESENVOLVIMENTO | B15: Moderado | C15: DESENVOLVIMENTO | D15: 0.1
A16: =B16&"-"&C16 -> Moderado-HOTELARIA | B16: Moderado | C16: HOTELARIA | D16: 0.1
A17: =B17&"-"&C17 -> Agressivo-PAPEL | B17: Agressivo | C17: PAPEL | D17: 0.35
A18: =B18&"-"&C18 -> Agressivo-TIJOLO | B18: Agressivo | C18: TIJOLO | D18: 0.15
A19: =B19&"-"&C19 -> Agressivo-HÍBRIDOS | B19: Agressivo | C19: HÍBRIDOS | D19: 0.05
... A22: =B22&"-"&C22 -> Agressivo-HOTELARIA | B22: Agressivo | C22: HOTELARIA | D22: 0.15
